[
    {
        "Full URL": "urn:uuid:a1a7c0c0-2a10-491c-aa30-73b070245e19",
        "ID": "a1a7c0c0-2a10-491c-aa30-73b070245e19",
        "Last Updated": "2024-09-10T17:01:10.667+00:00",
        "Name": "Sherri Fry",
        "Address": "1111 Example St, PHILADELPHIA, PA, USA - 88776",
        "Telecom": [
            {
                "Use": "mobile",
                "Value": "+1-222-333-4444",
                "System": "phone"
            },
            {
                "Use": "home",
                "Value": "+1-222-333-4567",
                "System": "phone"
            }
        ],
        "Relationship": "Mother"
    },
    {
        "Full URL": "urn:uuid:dae43d3b-5b6d-45ca-87b2-6fe380b733f4",
        "ID": "dae43d3b-5b6d-45ca-87b2-6fe380b733f4",
        "Last Updated": "2024-09-10T17:01:10.729+00:00",
        "Name": "Yancy Fry, Sr.",
        "Address": "",
        "Telecom": [
            {
                "Use": "home",
                "Value": "+1-222-333-4567",
                "System": "phone"
            },
            {
                "Use": "work",
                "Value": "+1-222-333-0000",
                "System": "phone"
            }
        ],
        "Relationship": "Father"
    }
]